ermine/__init__.py
ermine/app.py
ermine/enum.py
ermine/groups.py
ermine/injections.py
ermine/plugs/__init__.py
ermine/plugs/alternator.py
ermine/plugs/event.py
ermine/plugs/routable.py
ermine/plugs/static.py
ermine/request.py
ermine/response.py
ermine/static.py
ermine/templating.py
ermine-0.4.5.dist-info/WHEEL
ermine-0.4.5.dist-info/METADATA
ermine-0.4.5.dist-info/RECORD
