Metadata-Version: 2.1
Name: ermine
Version: 0.4.5
Summary: Nimble trough the web
Author: cheetahbyte
Author-email: bernerdoodle@outlook.de
Requires-Python: >=3.10,<4.0
Classifier: Programming Language :: Python :: 3
Classifier: Programming Language :: Python :: 3.10
Requires-Dist: multidict (>=6.0.2,<7.0.0)
Requires-Dist: pydantic (>=1.9.0,<2.0.0)
Requires-Dist: radish-router (>=0.1.1,<0.2.0)
Requires-Dist: wire-fuchs (>=0.1.0,<0.2.0)
